duplipy/__init__.py
duplipy/formatting.py
duplipy/replication.py
duplipy/similarity.py
duplipy/text_analysis.py
duplipy-0.2.5.dist-info/licenses/LICENSE
duplipy-0.2.5.dist-info/METADATA
duplipy-0.2.5.dist-info/WHEEL
duplipy-0.2.5.dist-info/top_level.txt
duplipy-0.2.5.dist-info/RECORD
