Metadata-Version: 2.4
Name: duplipy
Version: 0.2.5
Summary: DupliPy is a quick and easy-to-use package that can handle text formatting and data augmentation tasks for NLP in Python, with added support for image augmentation.
Home-page: https://github.com/infinitode/duplipy
Author: Infinitode Pty Ltd
Author-email: infinitode.ltd@gmail.com
Classifier: Development Status :: 5 - Production/Stable
Classifier: Intended Audience :: Developers
Classifier: License :: OSI Approved :: MIT License
Classifier: Programming Language :: Python :: 3
Classifier: Programming Language :: Python :: 3.6
Classifier: Programming Language :: Python :: 3.7
Classifier: Programming Language :: Python :: 3.8
Classifier: Programming Language :: Python :: 3.9
Classifier: Programming Language :: Python :: 3.10
Classifier: Programming Language :: Python :: 3.11
Classifier: Programming Language :: Python :: 3.12
Requires-Python: >=3.6
License-File: LICENSE
Requires-Dist: nltk
Requires-Dist: numpy
Requires-Dist: langcodes
Requires-Dist: joblib
Requires-Dist: tqdm
Requires-Dist: pillow
Requires-Dist: valx
Dynamic: author
Dynamic: author-email
Dynamic: classifier
Dynamic: description
Dynamic: description-content-type
Dynamic: home-page
Dynamic: license-file
Dynamic: requires-dist
Dynamic: requires-python
Dynamic: summary
